GoYuyanGaojiBiancheng/README.md
GoYuyanGaojiBiancheng/__init__.py
GoYuyanGaojiBiancheng/__main__.py
GoYuyanGaojiBiancheng/file.epub
GoYuyanGaojiBiancheng/index.html
GoYuyanGaojiBiancheng/css/__init__.py
GoYuyanGaojiBiancheng/css/annotations.css
GoYuyanGaojiBiancheng/css/main.css
GoYuyanGaojiBiancheng/css/normalize.css
GoYuyanGaojiBiancheng/css/popup.css
GoYuyanGaojiBiancheng/font/__init__.py
GoYuyanGaojiBiancheng/font/fontello.eot
GoYuyanGaojiBiancheng/font/fontello.svg
GoYuyanGaojiBiancheng/font/fontello.ttf
GoYuyanGaojiBiancheng/font/fontello.woff
GoYuyanGaojiBiancheng/img/__init__.py
GoYuyanGaojiBiancheng/img/annotator-glyph-sprite.png
GoYuyanGaojiBiancheng/img/annotator-icon-sprite.png
GoYuyanGaojiBiancheng/img/apple-touch-icon.png
GoYuyanGaojiBiancheng/img/cancelfullscreen.png
GoYuyanGaojiBiancheng/img/close.png
GoYuyanGaojiBiancheng/img/fullscreen.png
GoYuyanGaojiBiancheng/img/loader.gif
GoYuyanGaojiBiancheng/img/menu-icon.png
GoYuyanGaojiBiancheng/img/save.png
GoYuyanGaojiBiancheng/img/saved.png
GoYuyanGaojiBiancheng/img/settings-s.png
GoYuyanGaojiBiancheng/img/settings.png
GoYuyanGaojiBiancheng/img/star.png
GoYuyanGaojiBiancheng/js/__init__.py
GoYuyanGaojiBiancheng/js/epub.js
GoYuyanGaojiBiancheng/js/epub.min.js
GoYuyanGaojiBiancheng/js/epub.min.map
GoYuyanGaojiBiancheng/js/hooks.min.js
GoYuyanGaojiBiancheng/js/hooks.min.map
GoYuyanGaojiBiancheng/js/reader.js
GoYuyanGaojiBiancheng/js/reader.js.map
GoYuyanGaojiBiancheng/js/reader.min.js
GoYuyanGaojiBiancheng/js/reader.min.map
GoYuyanGaojiBiancheng/js/hooks/__init__.py
GoYuyanGaojiBiancheng/js/hooks/extensions/__init__.py
GoYuyanGaojiBiancheng/js/hooks/extensions/highlight.js
GoYuyanGaojiBiancheng/js/libs/__init__.py
GoYuyanGaojiBiancheng/js/libs/jquery.min.js
GoYuyanGaojiBiancheng/js/libs/localforage.min.js
GoYuyanGaojiBiancheng/js/libs/screenfull.js
GoYuyanGaojiBiancheng/js/libs/screenfull.min.js
GoYuyanGaojiBiancheng/js/libs/zip.min.js
GoYuyanGaojiBiancheng/js/plugins/__init__.py
go_yuyan_gaoji_biancheng-2024.3.4.0.dist-info/METADATA
go_yuyan_gaoji_biancheng-2024.3.4.0.dist-info/WHEEL
go_yuyan_gaoji_biancheng-2024.3.4.0.dist-info/entry_points.txt
go_yuyan_gaoji_biancheng-2024.3.4.0.dist-info/top_level.txt
go_yuyan_gaoji_biancheng-2024.3.4.0.dist-info/RECORD
